{
  "format_version": "1.12",
  "minecraft:recipe_shaped": {
    "description": {
      "identifier": "nicothekid:craft_x_azalea"
    },
    "tags": [
      "crafting_table"
    ],
    "pattern": [
      "A",
      "B"
    ],
    "key": {
      "A": {
        "item": "minecraft:azalea_leaves",
        "data": 0
      },
      "B": {
        "item": "minecraft:deadbush",
        "data": 0
      }
    },
    "result": {
      "item": "minecraft:azalea",
      "data": 0,
      "count": 1
    }
  }
}
